lullaby/__init__.py
lullaby/long_polling.py
lullaby/lullaby.py
lullaby-0.2.dist-info/METADATA
lullaby-0.2.dist-info/WHEEL
lullaby-0.2.dist-info/top_level.txt
lullaby-0.2.dist-info/RECORD
