Metadata-Version: 2.1
Name: lullaby
Version: 0.2
Summary: Telegram Bot API Python wrapper.
Home-page: https://github.com/andrekornyk/Lullaby-Library-by-DexTeam/
Author: DexTeam
Author-email: bankcommandoofficial@gmail.com
Keywords: telegram bot api lullaby
Classifier: Development Status :: 3 - Alpha
Classifier: Environment :: Console
Classifier: Intended Audience :: Developers
Classifier: Intended Audience :: Science/Research
Classifier: License :: OSI Approved :: MIT License
Classifier: Programming Language :: Python :: 3
Classifier: Programming Language :: Python :: 3.4
Classifier: Programming Language :: Python :: 3.5
Classifier: Programming Language :: Python :: 3.6
Classifier: Topic :: Software Development :: Libraries :: Python Modules
Requires-Dist: requests ==2.31.0
